[
{"Designer Brand": "\r\n\r\n                                                                                                        08Sircus\r\n                                                                                                            ", "Number of Prds on sale": ["15 products"]}
][
{"Designer Brand": "\r\n\r\n                                                                                                        08Sircus\r\n                                                                                                            ", "Number of Prds on sale": ["15 products"]}
][
{"Designer Brand": "\r\n\r\n                                                                                                        08Sircus\r\n                                                                                                            ", "Number of Prds on sale": ["15 products"]},
{"Designer Brand": null, "Prd Sale Price": null, "Discount": null, "Prd Price": null, "Prd Name": [], "Size": []}
][
{"Designer Brand": "\r\n\r\n                                                                                                        08Sircus\r\n                                                                                                            ", "Number of Prds on sale": ["15 products"]},
{"Size": []}
][
{"Designer Brand": "\r\n\r\n                                                                                                        08Sircus\r\n                                                                                                            ", "Number of Prds on sale": ["15 products"]},
{"Discount": null, "Designer Brand": null, "Prd Name": [], "Prd sale Price": null, "Size": []}
][
{"Designer Brand": "\r\n\r\n                                                                                                        08Sircus\r\n                                                                                                            ", "Number of Prds on sale": ["15 products"]},
{"Discount": null, "Designer Brand": null, "Prd Name": [], "Prd sale Price": null, "Size": []}
]